<?xml version="1.0"?>
<NodeDefines xmlns:xsd="http://www.w3.org/2001/XMLSchema" xmlns:xsi="http://www.w3.org/2001/XMLSchema-instance">
  <nodeList>
    <GraphNodeDefine>
      <name>Float</name>
      <portList>
        <id>0</id>
        <valueType>Float</valueType>
        <portType>Input</portType>
        <isTrigger>false</isTrigger>
      </portList>
      <portList>
        <id>2</id>
        <valueType>String</valueType>
        <portType>Input</portType>
        <isTrigger>false</isTrigger>
      </portList>
      <portList>
        <id>1</id>
        <valueType>Float</valueType>
        <portType>Output</portType>
        <isTrigger>false</isTrigger>
      </portList>
    </GraphNodeDefine>
    <GraphNodeDefine>
      <name>BinaryOp</name>
      <portList>
        <id>0</id>
        <valueType>Float</valueType>
        <portType>Input</portType>
        <isTrigger>false</isTrigger>
      </portList>
      <portList>
        <id>1</id>
        <valueType>Float</valueType>
        <portType>Input</portType>
        <isTrigger>false</isTrigger>
      </portList>
      <portList>
        <id>2</id>
        <valueType>Float</valueType>
        <portType>Output</portType>
        <isTrigger>false</isTrigger>
      </portList>
    </GraphNodeDefine>
  </nodeList>
</NodeDefines>